CHANGES.txt
LICENSE.txt
MANIFEST.in
README.txt
setup.cfg
setup.py
teamstuff_api.egg-info/PKG-INFO
teamstuff_api.egg-info/SOURCES.txt
teamstuff_api.egg-info/dependency_links.txt
teamstuff_api.egg-info/pbr.json
teamstuff_api.egg-info/top_level.txt
teamstuffapi/__init__.py