Metadata-Version: 1.0
Name: teamstuff-api
Version: 0.1.3
Summary: UNKNOWN
Home-page: https://gitlab.com/tomwerneruk/teamstuff-api
Author: Tom Werner
Author-email: hello@tomwerner.me.uk
License: MIT
Platform: UNKNOWN
